pyframe/__init__.py
pyframe/api.py
pyframe/middleware.py
pyframe/response.py
pyframe2-0.1.1.dist-info/METADATA
pyframe2-0.1.1.dist-info/WHEEL
pyframe2-0.1.1.dist-info/top_level.txt
pyframe2-0.1.1.dist-info/RECORD
